{
  "openapi": "3.0.4",
  "info": {
    "title": "VeiculoVerde.Api",
    "version": "1.0"
  },
  "paths": {
    "/api/AnaliseImpacto/por-regiao": {
      "get": {
        "tags": [
          "AnaliseImpacto"
        ],
        "parameters": [
          {
            "name": "cep",
            "in": "query",
            "schema": {
              "type": "string"
            }
          },
          {
            "name": "cidade",
            "in": "query",
            "schema": {
              "type": "string"
            }
          },
          {
            "name": "estado",
            "in": "query",
            "schema": {
              "type": "string"
            }
          }
        ],
        "responses": {
          "200": {
            "description": "OK",
            "content": {
              "text/plain": {
                "schema": {
                  "$ref": "#/components/schemas/ImpactoAmbientalDTO"
                }
              },
              "application/json": {
                "schema": {
                  "$ref": "#/components/schemas/ImpactoAmbientalDTO"
                }
              },
              "text/json": {
                "schema": {
                  "$ref": "#/components/schemas/ImpactoAmbientalDTO"
                }
              }
            }
          },
          "404": {
            "description": "Not Found",
            "content": {
              "text/plain": {
                "schema": {
                  "$ref": "#/components/schemas/ProblemDetails"
                }
              },
              "application/json": {
                "schema": {
                  "$ref": "#/components/schemas/ProblemDetails"
                }
              },
              "text/json": {
                "schema": {
                  "$ref": "#/components/schemas/ProblemDetails"
                }
              }
            }
          }
        }
      }
    },
    "/api/AnaliseImpacto/lista-paginada": {
      "get": {
        "tags": [
          "AnaliseImpacto"
        ],
        "parameters": [
          {
            "name": "pageNumber",
            "in": "query",
            "schema": {
              "type": "integer",
              "format": "int32",
              "default": 1
            }
          },
          {
            "name": "pageSize",
            "in": "query",
            "schema": {
              "type": "integer",
              "format": "int32",
              "default": 10
            }
          },
          {
            "name": "cep",
            "in": "query",
            "schema": {
              "type": "string"
            }
          },
          {
            "name": "cidade",
            "in": "query",
            "schema": {
              "type": "string"
            }
          },
          {
            "name": "estado",
            "in": "query",
            "schema": {
              "type": "string"
            }
          }
        ],
        "responses": {
          "200": {
            "description": "OK",
            "content": {
              "text/plain": {
                "schema": {
                  "$ref": "#/components/schemas/ImpactoAmbientalDTOPaginatedResultDTO"
                }
              },
              "application/json": {
                "schema": {
                  "$ref": "#/components/schemas/ImpactoAmbientalDTOPaginatedResultDTO"
                }
              },
              "text/json": {
                "schema": {
                  "$ref": "#/components/schemas/ImpactoAmbientalDTOPaginatedResultDTO"
                }
              }
            }
          }
        }
      }
    },
    "/api/Incentivos": {
      "get": {
        "tags": [
          "Incentivos"
        ],
        "parameters": [
          {
            "name": "tipoVeiculoSubstituto",
            "in": "query",
            "schema": {
              "type": "string"
            }
          },
          {
            "name": "estado",
            "in": "query",
            "schema": {
              "type": "string"
            }
          }
        ],
        "responses": {
          "200": {
            "description": "OK",
            "content": {
              "text/plain": {
                "schema": {
                  "type": "array",
                  "items": {
                    "$ref": "#/components/schemas/SugestaoIncentivoDTO"
                  }
                }
              },
              "application/json": {
                "schema": {
                  "type": "array",
                  "items": {
                    "$ref": "#/components/schemas/SugestaoIncentivoDTO"
                  }
                }
              },
              "text/json": {
                "schema": {
                  "type": "array",
                  "items": {
                    "$ref": "#/components/schemas/SugestaoIncentivoDTO"
                  }
                }
              }
            }
          }
        }
      }
    },
    "/api/Projecao/{anosParaFrente}": {
      "get": {
        "tags": [
          "Projecao"
        ],
        "parameters": [
          {
            "name": "anosParaFrente",
            "in": "path",
            "required": true,
            "schema": {
              "type": "integer",
              "format": "int32"
            }
          }
        ],
        "responses": {
          "200": {
            "description": "OK",
            "content": {
              "text/plain": {
                "schema": {
                  "type": "array",
                  "items": {
                    "$ref": "#/components/schemas/ProjecaoDTO"
                  }
                }
              },
              "application/json": {
                "schema": {
                  "type": "array",
                  "items": {
                    "$ref": "#/components/schemas/ProjecaoDTO"
                  }
                }
              },
              "text/json": {
                "schema": {
                  "type": "array",
                  "items": {
                    "$ref": "#/components/schemas/ProjecaoDTO"
                  }
                }
              }
            }
          },
          "400": {
            "description": "Bad Request",
            "content": {
              "text/plain": {
                "schema": {
                  "$ref": "#/components/schemas/ProblemDetails"
                }
              },
              "application/json": {
                "schema": {
                  "$ref": "#/components/schemas/ProblemDetails"
                }
              },
              "text/json": {
                "schema": {
                  "$ref": "#/components/schemas/ProblemDetails"
                }
              }
            }
          }
        }
      }
    },
    "/api/VeiculoSubstituicao": {
      "post": {
        "tags": [
          "VeiculoSubstituicao"
        ],
        "requestBody": {
          "content": {
            "application/json": {
              "schema": {
                "$ref": "#/components/schemas/VeiculoSubstituidoDTO"
              }
            },
            "text/json": {
              "schema": {
                "$ref": "#/components/schemas/VeiculoSubstituidoDTO"
              }
            },
            "application/*+json": {
              "schema": {
                "$ref": "#/components/schemas/VeiculoSubstituidoDTO"
              }
            }
          }
        },
        "responses": {
          "201": {
            "description": "Created",
            "content": {
              "text/plain": {
                "schema": {
                  "$ref": "#/components/schemas/VeiculoSubstituidoDTO"
                }
              },
              "application/json": {
                "schema": {
                  "$ref": "#/components/schemas/VeiculoSubstituidoDTO"
                }
              },
              "text/json": {
                "schema": {
                  "$ref": "#/components/schemas/VeiculoSubstituidoDTO"
                }
              }
            }
          },
          "400": {
            "description": "Bad Request",
            "content": {
              "text/plain": {
                "schema": {
                  "$ref": "#/components/schemas/ProblemDetails"
                }
              },
              "application/json": {
                "schema": {
                  "$ref": "#/components/schemas/ProblemDetails"
                }
              },
              "text/json": {
                "schema": {
                  "$ref": "#/components/schemas/ProblemDetails"
                }
              }
            }
          }
        }
      },
      "get": {
        "tags": [
          "VeiculoSubstituicao"
        ],
        "parameters": [
          {
            "name": "pageNumber",
            "in": "query",
            "schema": {
              "type": "integer",
              "format": "int32",
              "default": 1
            }
          },
          {
            "name": "pageSize",
            "in": "query",
            "schema": {
              "type": "integer",
              "format": "int32",
              "default": 10
            }
          }
        ],
        "responses": {
          "200": {
            "description": "OK",
            "content": {
              "text/plain": {
                "schema": {
                  "$ref": "#/components/schemas/VeiculoSubstituidoDTOPaginatedResultDTO"
                }
              },
              "application/json": {
                "schema": {
                  "$ref": "#/components/schemas/VeiculoSubstituidoDTOPaginatedResultDTO"
                }
              },
              "text/json": {
                "schema": {
                  "$ref": "#/components/schemas/VeiculoSubstituidoDTOPaginatedResultDTO"
                }
              }
            }
          }
        }
      }
    },
    "/api/VeiculoSubstituicao/{id}": {
      "get": {
        "tags": [
          "VeiculoSubstituicao"
        ],
        "parameters": [
          {
            "name": "id",
            "in": "path",
            "required": true,
            "schema": {
              "type": "integer",
              "format": "int32"
            }
          }
        ],
        "responses": {
          "200": {
            "description": "OK",
            "content": {
              "text/plain": {
                "schema": {
                  "$ref": "#/components/schemas/VeiculoSubstituidoDTO"
                }
              },
              "application/json": {
                "schema": {
                  "$ref": "#/components/schemas/VeiculoSubstituidoDTO"
                }
              },
              "text/json": {
                "schema": {
                  "$ref": "#/components/schemas/VeiculoSubstituidoDTO"
                }
              }
            }
          },
          "404": {
            "description": "Not Found",
            "content": {
              "text/plain": {
                "schema": {
                  "$ref": "#/components/schemas/ProblemDetails"
                }
              },
              "application/json": {
                "schema": {
                  "$ref": "#/components/schemas/ProblemDetails"
                }
              },
              "text/json": {
                "schema": {
                  "$ref": "#/components/schemas/ProblemDetails"
                }
              }
            }
          }
        }
      }
    }
  },
  "components": {
    "schemas": {
      "ImpactoAmbientalDTO": {
        "type": "object",
        "properties": {
          "cep": {
            "type": "string",
            "nullable": true
          },
          "cidade": {
            "type": "string",
            "nullable": true
          },
          "estado": {
            "type": "string",
            "nullable": true
          },
          "reducaoCO2TotalKg": {
            "type": "number",
            "format": "double"
          },
          "economiaCombustivelTotalLitros": {
            "type": "number",
            "format": "double"
          },
          "numeroSubstituicoes": {
            "type": "integer",
            "format": "int32"
          },
          "dataAnalise": {
            "type": "string",
            "format": "date-time"
          }
        },
        "additionalProperties": false
      },
      "ImpactoAmbientalDTOPaginatedResultDTO": {
        "type": "object",
        "properties": {
          "items": {
            "type": "array",
            "items": {
              "$ref": "#/components/schemas/ImpactoAmbientalDTO"
            },
            "nullable": true
          },
          "totalCount": {
            "type": "integer",
            "format": "int32"
          },
          "pageNumber": {
            "type": "integer",
            "format": "int32"
          },
          "pageSize": {
            "type": "integer",
            "format": "int32"
          },
          "totalPages": {
            "type": "integer",
            "format": "int32",
            "readOnly": true
          },
          "hasPreviousPage": {
            "type": "boolean",
            "readOnly": true
          },
          "hasNextPage": {
            "type": "boolean",
            "readOnly": true
          }
        },
        "additionalProperties": false
      },
      "ProblemDetails": {
        "type": "object",
        "properties": {
          "type": {
            "type": "string",
            "nullable": true
          },
          "title": {
            "type": "string",
            "nullable": true
          },
          "status": {
            "type": "integer",
            "format": "int32",
            "nullable": true
          },
          "detail": {
            "type": "string",
            "nullable": true
          },
          "instance": {
            "type": "string",
            "nullable": true
          }
        },
        "additionalProperties": { }
      },
      "ProjecaoDTO": {
        "type": "object",
        "properties": {
          "ano": {
            "type": "integer",
            "format": "int32"
          },
          "mes": {
            "type": "integer",
            "format": "int32"
          },
          "veiculosProjetados": {
            "type": "integer",
            "format": "int32"
          },
          "reducaoCO2ProjetadaKg": {
            "type": "number",
            "format": "double"
          },
          "economiaCombustivelProjetadaLitros": {
            "type": "number",
            "format": "double"
          }
        },
        "additionalProperties": false
      },
      "SugestaoIncentivoDTO": {
        "type": "object",
        "properties": {
          "tipoIncentivo": {
            "type": "string",
            "nullable": true
          },
          "descricao": {
            "type": "string",
            "nullable": true
          },
          "linkMaisInformacoes": {
            "type": "string",
            "nullable": true
          },
          "elegibilidade": {
            "type": "string",
            "nullable": true
          },
          "valorEstimadoBeneficio": {
            "type": "number",
            "format": "double"
          }
        },
        "additionalProperties": false
      },
      "TipoVeiculoSubstituto": {
        "enum": [
          0,
          1,
          2,
          3
        ],
        "type": "integer",
        "format": "int32"
      },
      "VeiculoSubstituidoDTO": {
        "required": [
          "cep",
          "cidade",
          "dataSubstituicao",
          "estado",
          "marcaVeiculoCombustao",
          "marcaVeiculoSubstituto",
          "modeloVeiculoCombustao",
          "modeloVeiculoSubstituto",
          "placaVeiculoCombustao",
          "tipoVeiculoSubstituto"
        ],
        "type": "object",
        "properties": {
          "id": {
            "type": "integer",
            "format": "int32"
          },
          "placaVeiculoCombustao": {
            "maxLength": 10,
            "minLength": 0,
            "type": "string"
          },
          "marcaVeiculoCombustao": {
            "minLength": 1,
            "type": "string"
          },
          "modeloVeiculoCombustao": {
            "minLength": 1,
            "type": "string"
          },
          "anoFabricacaoVeiculoCombustao": {
            "maximum": 2025,
            "minimum": 1900,
            "type": "integer",
            "format": "int32"
          },
          "emissaoCO2Anterior": {
            "maximum": 1000,
            "minimum": 0,
            "type": "number",
            "format": "double"
          },
          "consumoCombustivelAnteriorKmPorLitro": {
            "maximum": 100,
            "minimum": 0,
            "type": "number",
            "format": "double"
          },
          "tipoVeiculoSubstituto": {
            "$ref": "#/components/schemas/TipoVeiculoSubstituto"
          },
          "marcaVeiculoSubstituto": {
            "minLength": 1,
            "type": "string"
          },
          "modeloVeiculoSubstituto": {
            "minLength": 1,
            "type": "string"
          },
          "emissaoCO2Nova": {
            "maximum": 1000,
            "minimum": 0,
            "type": "number",
            "format": "double"
          },
          "autonomiaVeiculoSubstitutoKm": {
            "maximum": 10000,
            "minimum": 0,
            "type": "number",
            "format": "double"
          },
          "dataSubstituicao": {
            "type": "string",
            "format": "date-time"
          },
          "cep": {
            "maxLength": 8,
            "minLength": 8,
            "type": "string"
          },
          "cidade": {
            "minLength": 1,
            "type": "string"
          },
          "estado": {
            "maxLength": 2,
            "minLength": 2,
            "type": "string"
          },
          "pais": {
            "type": "string",
            "nullable": true
          }
        },
        "additionalProperties": false
      },
      "VeiculoSubstituidoDTOPaginatedResultDTO": {
        "type": "object",
        "properties": {
          "items": {
            "type": "array",
            "items": {
              "$ref": "#/components/schemas/VeiculoSubstituidoDTO"
            },
            "nullable": true
          },
          "totalCount": {
            "type": "integer",
            "format": "int32"
          },
          "pageNumber": {
            "type": "integer",
            "format": "int32"
          },
          "pageSize": {
            "type": "integer",
            "format": "int32"
          },
          "totalPages": {
            "type": "integer",
            "format": "int32",
            "readOnly": true
          },
          "hasPreviousPage": {
            "type": "boolean",
            "readOnly": true
          },
          "hasNextPage": {
            "type": "boolean",
            "readOnly": true
          }
        },
        "additionalProperties": false
      }
    }
  }
}